{
  "股票代码": "SH600570",
  "quote": {
    "股票代码": "SH600570",
    "当前价格": 26.63,
    "涨跌幅(%)": -0.34,
    "涨跌额": -0.09,
    "开盘价": 26.55,
    "最高价": 26.77,
    "最低价": 26.27,
    "昨收价": 26.72,
    "成交量(手)": 20380371,
    "成交额(万)": 54041.54,
    "换手率(%)": 1.08,
    "振幅(%)": 1.87,
    "年初至今涨跌幅(%)": -11.67,
    "总市值(亿)": 504.28,
    "流通市值(亿)": 504.28,
    "平均价格": 26.516,
    "更新时间": 1776409200000
  },
  "daily_kline": [
    {
      "0": 1776355200000,
      "1": 20380371,
      "2": 26.55,
      "3": 26.77,
      "4": 26.27,
      "5": 26.63,
      "6": -0.09,
      "7": -0.34,
      "8": 1.08,
      "9": 540415416.0,
      "10": null,
      "11": null,
      "12": 40.9589,
      "13": 5.121,
      "14": 8.7201,
      "15": 47.2722,
      "16": 50427844695.46,
      "17": null,
      "18": null,
      "19": null,
      "20": null,
      "21": null,
      "22": null,
      "23": null
    }
  ],
  "money_flow": [
    {
      "时间": "2026-04-17 09:30",
      "资金流向(万元)": -804.21
    },
    {
      "时间": "2026-04-17 09:31",
      "资金流向(万元)": -462.75
    },
    {
      "时间": "2026-04-17 09:32",
      "资金流向(万元)": -722.53
    },
    {
      "时间": "2026-04-17 09:33",
      "资金流向(万元)": -1079.72
    },
    {
      "时间": "2026-04-17 09:34",
      "资金流向(万元)": -1048.88
    },
    {
      "时间": "2026-04-17 09:35",
      "资金流向(万元)": -1312.0
    },
    {
      "时间": "2026-04-17 09:36",
      "资金流向(万元)": -1102.6
    },
    {
      "时间": "2026-04-17 09:37",
      "资金流向(万元)": -1212.26
    },
    {
      "时间": "2026-04-17 09:38",
      "资金流向(万元)": -1218.06
    },
    {
      "时间": "2026-04-17 09:39",
      "资金流向(万元)": -1707.64
    },
    {
      "时间": "2026-04-17 09:40",
      "资金流向(万元)": -1948.81
    },
    {
      "时间": "2026-04-17 09:41",
      "资金流向(万元)": -1641.3
    },
    {
      "时间": "2026-04-17 09:42",
      "资金流向(万元)": -1665.37
    },
    {
      "时间": "2026-04-17 09:43",
      "资金流向(万元)": -1882.97
    },
    {
      "时间": "2026-04-17 09:44",
      "资金流向(万元)": -1894.97
    },
    {
      "时间": "2026-04-17 09:45",
      "资金流向(万元)": -1946.31
    },
    {
      "时间": "2026-04-17 09:46",
      "资金流向(万元)": -1823.52
    },
    {
      "时间": "2026-04-17 09:47",
      "资金流向(万元)": -1830.4
    },
    {
      "时间": "2026-04-17 09:48",
      "资金流向(万元)": -2031.62
    },
    {
      "时间": "2026-04-17 09:49",
      "资金流向(万元)": -2149.91
    },
    {
      "时间": "2026-04-17 09:50",
      "资金流向(万元)": -2265.47
    },
    {
      "时间": "2026-04-17 09:51",
      "资金流向(万元)": -1605.52
    },
    {
      "时间": "2026-04-17 09:52",
      "资金流向(万元)": -1771.17
    },
    {
      "时间": "2026-04-17 09:53",
      "资金流向(万元)": -1788.41
    },
    {
      "时间": "2026-04-17 09:54",
      "资金流向(万元)": -1831.64
    },
    {
      "时间": "2026-04-17 09:55",
      "资金流向(万元)": -1833.31
    },
    {
      "时间": "2026-04-17 09:56",
      "资金流向(万元)": -1936.58
    },
    {
      "时间": "2026-04-17 09:57",
      "资金流向(万元)": -2172.87
    },
    {
      "时间": "2026-04-17 09:58",
      "资金流向(万元)": -2210.67
    },
    {
      "时间": "2026-04-17 09:59",
      "资金流向(万元)": -2208.66
    },
    {
      "时间": "2026-04-17 10:00",
      "资金流向(万元)": -2210.07
    },
    {
      "时间": "2026-04-17 10:01",
      "资金流向(万元)": -2213.24
    },
    {
      "时间": "2026-04-17 10:02",
      "资金流向(万元)": -2511.76
    },
    {
      "时间": "2026-04-17 10:03",
      "资金流向(万元)": -2572.22
    },
    {
      "时间": "2026-04-17 10:04",
      "资金流向(万元)": -2632.47
    },
    {
      "时间": "2026-04-17 10:05",
      "资金流向(万元)": -2609.99
    },
    {
      "时间": "2026-04-17 10:06",
      "资金流向(万元)": -3809.34
    },
    {
      "时间": "2026-04-17 10:07",
      "资金流向(万元)": -3873.7
    },
    {
      "时间": "2026-04-17 10:08",
      "资金流向(万元)": -3799.88
    },
    {
      "时间": "2026-04-17 10:09",
      "资金流向(万元)": -4066.41
    },
    {
      "时间": "2026-04-17 10:10",
      "资金流向(万元)": -4015.03
    },
    {
      "时间": "2026-04-17 10:11",
      "资金流向(万元)": -4030.69
    },
    {
      "时间": "2026-04-17 10:12",
      "资金流向(万元)": -3926.84
    },
    {
      "时间": "2026-04-17 10:13",
      "资金流向(万元)": -4065.26
    },
    {
      "时间": "2026-04-17 10:14",
      "资金流向(万元)": -3893.21
    },
    {
      "时间": "2026-04-17 10:15",
      "资金流向(万元)": -3523.58
    },
    {
      "时间": "2026-04-17 10:16",
      "资金流向(万元)": -3520.95
    },
    {
      "时间": "2026-04-17 10:17",
      "资金流向(万元)": -3452.44
    },
    {
      "时间": "2026-04-17 10:18",
      "资金流向(万元)": -3499.74
    },
    {
      "时间": "2026-04-17 10:19",
      "资金流向(万元)": -3565.92
    },
    {
      "时间": "2026-04-17 10:20",
      "资金流向(万元)": -3552.22
    },
    {
      "时间": "2026-04-17 10:21",
      "资金流向(万元)": -3493.06
    },
    {
      "时间": "2026-04-17 10:22",
      "资金流向(万元)": -3340.47
    },
    {
      "时间": "2026-04-17 10:23",
      "资金流向(万元)": -3352.1
    },
    {
      "时间": "2026-04-17 10:24",
      "资金流向(万元)": -3372.06
    },
    {
      "时间": "2026-04-17 10:25",
      "资金流向(万元)": -3432.76
    },
    {
      "时间": "2026-04-17 10:26",
      "资金流向(万元)": -3377.06
    },
    {
      "时间": "2026-04-17 10:27",
      "资金流向(万元)": -3262.69
    },
    {
      "时间": "2026-04-17 10:28",
      "资金流向(万元)": -3092.21
    },
    {
      "时间": "2026-04-17 10:29",
      "资金流向(万元)": -2838.48
    },
    {
      "时间": "2026-04-17 10:30",
      "资金流向(万元)": -2818.1
    },
    {
      "时间": "2026-04-17 10:31",
      "资金流向(万元)": -2615.88
    },
    {
      "时间": "2026-04-17 10:32",
      "资金流向(万元)": -2413.65
    },
    {
      "时间": "2026-04-17 10:33",
      "资金流向(万元)": -2144.08
    },
    {
      "时间": "2026-04-17 10:34",
      "资金流向(万元)": -2008.84
    },
    {
      "时间": "2026-04-17 10:35",
      "资金流向(万元)": -1940.71
    },
    {
      "时间": "2026-04-17 10:36",
      "资金流向(万元)": -2032.94
    },
    {
      "时间": "2026-04-17 10:37",
      "资金流向(万元)": -1862.54
    },
    {
      "时间": "2026-04-17 10:38",
      "资金流向(万元)": -1910.5
    },
    {
      "时间": "2026-04-17 10:39",
      "资金流向(万元)": -1911.56
    },
    {
      "时间": "2026-04-17 10:40",
      "资金流向(万元)": -1824.08
    },
    {
      "时间": "2026-04-17 10:41",
      "资金流向(万元)": -1790.93
    },
    {
      "时间": "2026-04-17 10:42",
      "资金流向(万元)": -1662.82
    },
    {
      "时间": "2026-04-17 10:43",
      "资金流向(万元)": -1730.99
    },
    {
      "时间": "2026-04-17 10:44",
      "资金流向(万元)": -1785.6
    },
    {
      "时间": "2026-04-17 10:45",
      "资金流向(万元)": -1630.96
    },
    {
      "时间": "2026-04-17 10:46",
      "资金流向(万元)": -1390.82
    },
    {
      "时间": "2026-04-17 10:47",
      "资金流向(万元)": -1377.0
    },
    {
      "时间": "2026-04-17 10:48",
      "资金流向(万元)": -1396.13
    },
    {
      "时间": "2026-04-17 10:49",
      "资金流向(万元)": -1409.12
    },
    {
      "时间": "2026-04-17 10:50",
      "资金流向(万元)": -1336.4
    },
    {
      "时间": "2026-04-17 10:51",
      "资金流向(万元)": -1428.98
    },
    {
      "时间": "2026-04-17 10:52",
      "资金流向(万元)": -1558.08
    },
    {
      "时间": "2026-04-17 10:53",
      "资金流向(万元)": -1758.47
    },
    {
      "时间": "2026-04-17 10:54",
      "资金流向(万元)": -1768.02
    },
    {
      "时间": "2026-04-17 10:55",
      "资金流向(万元)": -1730.05
    },
    {
      "时间": "2026-04-17 10:56",
      "资金流向(万元)": -1714.65
    },
    {
      "时间": "2026-04-17 10:57",
      "资金流向(万元)": -1788.12
    },
    {
      "时间": "2026-04-17 10:58",
      "资金流向(万元)": -1810.91
    },
    {
      "时间": "2026-04-17 10:59",
      "资金流向(万元)": -1834.24
    },
    {
      "时间": "2026-04-17 11:00",
      "资金流向(万元)": -1849.07
    },
    {
      "时间": "2026-04-17 11:01",
      "资金流向(万元)": -1879.53
    },
    {
      "时间": "2026-04-17 11:02",
      "资金流向(万元)": -1867.59
    },
    {
      "时间": "2026-04-17 11:03",
      "资金流向(万元)": -1858.61
    },
    {
      "时间": "2026-04-17 11:04",
      "资金流向(万元)": -1884.85
    },
    {
      "时间": "2026-04-17 11:05",
      "资金流向(万元)": -1923.02
    },
    {
      "时间": "2026-04-17 11:06",
      "资金流向(万元)": -1902.59
    },
    {
      "时间": "2026-04-17 11:07",
      "资金流向(万元)": -1958.17
    },
    {
      "时间": "2026-04-17 11:08",
      "资金流向(万元)": -1830.72
    },
    {
      "时间": "2026-04-17 11:09",
      "资金流向(万元)": -1834.97
    },
    {
      "时间": "2026-04-17 11:10",
      "资金流向(万元)": -1907.58
    },
    {
      "时间": "2026-04-17 11:11",
      "资金流向(万元)": -1874.44
    },
    {
      "时间": "2026-04-17 11:12",
      "资金流向(万元)": -1787.16
    },
    {
      "时间": "2026-04-17 11:13",
      "资金流向(万元)": -1828.26
    },
    {
      "时间": "2026-04-17 11:14",
      "资金流向(万元)": -1877.32
    },
    {
      "时间": "2026-04-17 11:15",
      "资金流向(万元)": -1814.97
    },
    {
      "时间": "2026-04-17 11:16",
      "资金流向(万元)": -1838.04
    },
    {
      "时间": "2026-04-17 11:17",
      "资金流向(万元)": -1823.18
    },
    {
      "时间": "2026-04-17 11:18",
      "资金流向(万元)": -1888.68
    },
    {
      "时间": "2026-04-17 11:19",
      "资金流向(万元)": -1940.61
    },
    {
      "时间": "2026-04-17 11:20",
      "资金流向(万元)": -2239.48
    },
    {
      "时间": "2026-04-17 11:21",
      "资金流向(万元)": -2277.36
    },
    {
      "时间": "2026-04-17 11:22",
      "资金流向(万元)": -2213.8
    },
    {
      "时间": "2026-04-17 11:23",
      "资金流向(万元)": -2236.05
    },
    {
      "时间": "2026-04-17 11:24",
      "资金流向(万元)": -2207.46
    },
    {
      "时间": "2026-04-17 11:25",
      "资金流向(万元)": -2255.45
    },
    {
      "时间": "2026-04-17 11:26",
      "资金流向(万元)": -2300.21
    },
    {
      "时间": "2026-04-17 11:27",
      "资金流向(万元)": -2243.27
    },
    {
      "时间": "2026-04-17 11:28",
      "资金流向(万元)": -2247.23
    },
    {
      "时间": "2026-04-17 11:29",
      "资金流向(万元)": -2247.76
    },
    {
      "时间": "2026-04-17 11:30",
      "资金流向(万元)": -2247.76
    },
    {
      "时间": "2026-04-17 13:00",
      "资金流向(万元)": -2176.73
    },
    {
      "时间": "2026-04-17 13:01",
      "资金流向(万元)": -2446.52
    },
    {
      "时间": "2026-04-17 13:02",
      "资金流向(万元)": -2566.03
    },
    {
      "时间": "2026-04-17 13:03",
      "资金流向(万元)": -2470.42
    },
    {
      "时间": "2026-04-17 13:04",
      "资金流向(万元)": -2478.88
    },
    {
      "时间": "2026-04-17 13:05",
      "资金流向(万元)": -2486.02
    },
    {
      "时间": "2026-04-17 13:06",
      "资金流向(万元)": -2578.31
    },
    {
      "时间": "2026-04-17 13:07",
      "资金流向(万元)": -2642.45
    },
    {
      "时间": "2026-04-17 13:08",
      "资金流向(万元)": -2705.6
    },
    {
      "时间": "2026-04-17 13:09",
      "资金流向(万元)": -2579.99
    },
    {
      "时间": "2026-04-17 13:10",
      "资金流向(万元)": -2529.19
    },
    {
      "时间": "2026-04-17 13:11",
      "资金流向(万元)": -2471.23
    },
    {
      "时间": "2026-04-17 13:12",
      "资金流向(万元)": -2462.49
    },
    {
      "时间": "2026-04-17 13:13",
      "资金流向(万元)": -2320.88
    },
    {
      "时间": "2026-04-17 13:14",
      "资金流向(万元)": -2314.84
    },
    {
      "时间": "2026-04-17 13:15",
      "资金流向(万元)": -2308.48
    },
    {
      "时间": "2026-04-17 13:16",
      "资金流向(万元)": -2245.27
    },
    {
      "时间": "2026-04-17 13:17",
      "资金流向(万元)": -2207.91
    },
    {
      "时间": "2026-04-17 13:18",
      "资金流向(万元)": -2237.04
    },
    {
      "时间": "2026-04-17 13:19",
      "资金流向(万元)": -2059.08
    },
    {
      "时间": "2026-04-17 13:20",
      "资金流向(万元)": -2013.48
    },
    {
      "时间": "2026-04-17 13:21",
      "资金流向(万元)": -2011.35
    },
    {
      "时间": "2026-04-17 13:22",
      "资金流向(万元)": -1923.84
    },
    {
      "时间": "2026-04-17 13:23",
      "资金流向(万元)": -1861.49
    },
    {
      "时间": "2026-04-17 13:24",
      "资金流向(万元)": -1605.25
    },
    {
      "时间": "2026-04-17 13:25",
      "资金流向(万元)": -1631.82
    },
    {
      "时间": "2026-04-17 13:26",
      "资金流向(万元)": -1543.79
    },
    {
      "时间": "2026-04-17 13:27",
      "资金流向(万元)": -1539.79
    },
    {
      "时间": "2026-04-17 13:28",
      "资金流向(万元)": -1520.12
    },
    {
      "时间": "2026-04-17 13:29",
      "资金流向(万元)": -1509.75
    },
    {
      "时间": "2026-04-17 13:30",
      "资金流向(万元)": -1566.06
    },
    {
      "时间": "2026-04-17 13:31",
      "资金流向(万元)": -1530.71
    },
    {
      "时间": "2026-04-17 13:32",
      "资金流向(万元)": -1525.4
    },
    {
      "时间": "2026-04-17 13:33",
      "资金流向(万元)": -1598.4
    },
    {
      "时间": "2026-04-17 13:34",
      "资金流向(万元)": -1281.39
    },
    {
      "时间": "2026-04-17 13:35",
      "资金流向(万元)": -1203.75
    },
    {
      "时间": "2026-04-17 13:36",
      "资金流向(万元)": -1177.96
    },
    {
      "时间": "2026-04-17 13:37",
      "资金流向(万元)": -904.51
    },
    {
      "时间": "2026-04-17 13:38",
      "资金流向(万元)": -821.42
    },
    {
      "时间": "2026-04-17 13:39",
      "资金流向(万元)": -879.71
    },
    {
      "时间": "2026-04-17 13:40",
      "资金流向(万元)": -843.79
    },
    {
      "时间": "2026-04-17 13:41",
      "资金流向(万元)": -811.83
    },
    {
      "时间": "2026-04-17 13:42",
      "资金流向(万元)": -873.02
    },
    {
      "时间": "2026-04-17 13:43",
      "资金流向(万元)": -924.89
    },
    {
      "时间": "2026-04-17 13:44",
      "资金流向(万元)": -945.09
    },
    {
      "时间": "2026-04-17 13:45",
      "资金流向(万元)": -814.91
    },
    {
      "时间": "2026-04-17 13:46",
      "资金流向(万元)": -568.2
    },
    {
      "时间": "2026-04-17 13:47",
      "资金流向(万元)": 129.74
    },
    {
      "时间": "2026-04-17 13:48",
      "资金流向(万元)": 43.89
    },
    {
      "时间": "2026-04-17 13:49",
      "资金流向(万元)": 15.27
    },
    {
      "时间": "2026-04-17 13:50",
      "资金流向(万元)": -97.57
    },
    {
      "时间": "2026-04-17 13:51",
      "资金流向(万元)": -120.8
    },
    {
      "时间": "2026-04-17 13:52",
      "资金流向(万元)": -23.21
    },
    {
      "时间": "2026-04-17 13:53",
      "资金流向(万元)": -39.53
    },
    {
      "时间": "2026-04-17 13:54",
      "资金流向(万元)": -36.84
    },
    {
      "时间": "2026-04-17 13:55",
      "资金流向(万元)": 94.94
    },
    {
      "时间": "2026-04-17 13:56",
      "资金流向(万元)": 108.3
    },
    {
      "时间": "2026-04-17 13:57",
      "资金流向(万元)": -3.64
    },
    {
      "时间": "2026-04-17 13:58",
      "资金流向(万元)": -196.05
    },
    {
      "时间": "2026-04-17 13:59",
      "资金流向(万元)": -257.22
    },
    {
      "时间": "2026-04-17 14:00",
      "资金流向(万元)": 113.79
    },
    {
      "时间": "2026-04-17 14:01",
      "资金流向(万元)": 84.13
    },
    {
      "时间": "2026-04-17 14:02",
      "资金流向(万元)": -45.97
    },
    {
      "时间": "2026-04-17 14:03",
      "资金流向(万元)": -66.8
    },
    {
      "时间": "2026-04-17 14:04",
      "资金流向(万元)": -158.65
    },
    {
      "时间": "2026-04-17 14:05",
      "资金流向(万元)": -155.17
    },
    {
      "时间": "2026-04-17 14:06",
      "资金流向(万元)": -29.87
    },
    {
      "时间": "2026-04-17 14:07",
      "资金流向(万元)": -80.92
    },
    {
      "时间": "2026-04-17 14:08",
      "资金流向(万元)": -138.36
    },
    {
      "时间": "2026-04-17 14:09",
      "资金流向(万元)": -456.49
    },
    {
      "时间": "2026-04-17 14:10",
      "资金流向(万元)": -550.9
    },
    {
      "时间": "2026-04-17 14:11",
      "资金流向(万元)": -617.21
    },
    {
      "时间": "2026-04-17 14:12",
      "资金流向(万元)": -597.47
    },
    {
      "时间": "2026-04-17 14:13",
      "资金流向(万元)": -622.26
    },
    {
      "时间": "2026-04-17 14:14",
      "资金流向(万元)": -654.25
    },
    {
      "时间": "2026-04-17 14:15",
      "资金流向(万元)": -663.84
    },
    {
      "时间": "2026-04-17 14:16",
      "资金流向(万元)": -646.35
    },
    {
      "时间": "2026-04-17 14:17",
      "资金流向(万元)": -784.01
    },
    {
      "时间": "2026-04-17 14:18",
      "资金流向(万元)": -861.72
    },
    {
      "时间": "2026-04-17 14:19",
      "资金流向(万元)": -805.83
    },
    {
      "时间": "2026-04-17 14:20",
      "资金流向(万元)": -868.65
    },
    {
      "时间": "2026-04-17 14:21",
      "资金流向(万元)": -966.04
    },
    {
      "时间": "2026-04-17 14:22",
      "资金流向(万元)": -880.3
    },
    {
      "时间": "2026-04-17 14:23",
      "资金流向(万元)": -884.27
    },
    {
      "时间": "2026-04-17 14:24",
      "资金流向(万元)": -866.15
    },
    {
      "时间": "2026-04-17 14:25",
      "资金流向(万元)": -958.63
    },
    {
      "时间": "2026-04-17 14:26",
      "资金流向(万元)": -983.14
    },
    {
      "时间": "2026-04-17 14:27",
      "资金流向(万元)": -1063.32
    },
    {
      "时间": "2026-04-17 14:28",
      "资金流向(万元)": -1071.31
    },
    {
      "时间": "2026-04-17 14:29",
      "资金流向(万元)": -1142.41
    },
    {
      "时间": "2026-04-17 14:30",
      "资金流向(万元)": -1031.98
    },
    {
      "时间": "2026-04-17 14:31",
      "资金流向(万元)": -955.25
    },
    {
      "时间": "2026-04-17 14:32",
      "资金流向(万元)": -1020.0
    },
    {
      "时间": "2026-04-17 14:33",
      "资金流向(万元)": -954.68
    },
    {
      "时间": "2026-04-17 14:34",
      "资金流向(万元)": -866.38
    },
    {
      "时间": "2026-04-17 14:35",
      "资金流向(万元)": -841.03
    },
    {
      "时间": "2026-04-17 14:36",
      "资金流向(万元)": -778.83
    },
    {
      "时间": "2026-04-17 14:37",
      "资金流向(万元)": -751.6
    },
    {
      "时间": "2026-04-17 14:38",
      "资金流向(万元)": -807.34
    },
    {
      "时间": "2026-04-17 14:39",
      "资金流向(万元)": -814.54
    },
    {
      "时间": "2026-04-17 14:40",
      "资金流向(万元)": -874.0
    },
    {
      "时间": "2026-04-17 14:41",
      "资金流向(万元)": -564.44
    },
    {
      "时间": "2026-04-17 14:42",
      "资金流向(万元)": -645.94
    },
    {
      "时间": "2026-04-17 14:43",
      "资金流向(万元)": -639.81
    },
    {
      "时间": "2026-04-17 14:44",
      "资金流向(万元)": -558.83
    },
    {
      "时间": "2026-04-17 14:45",
      "资金流向(万元)": -587.87
    },
    {
      "时间": "2026-04-17 14:46",
      "资金流向(万元)": -339.32
    },
    {
      "时间": "2026-04-17 14:47",
      "资金流向(万元)": -319.32
    },
    {
      "时间": "2026-04-17 14:48",
      "资金流向(万元)": -332.89
    },
    {
      "时间": "2026-04-17 14:49",
      "资金流向(万元)": -368.05
    },
    {
      "时间": "2026-04-17 14:50",
      "资金流向(万元)": -369.1
    },
    {
      "时间": "2026-04-17 14:51",
      "资金流向(万元)": -330.48
    },
    {
      "时间": "2026-04-17 14:52",
      "资金流向(万元)": -195.93
    },
    {
      "时间": "2026-04-17 14:53",
      "资金流向(万元)": -75.28
    },
    {
      "时间": "2026-04-17 14:54",
      "资金流向(万元)": 70.93
    },
    {
      "时间": "2026-04-17 14:55",
      "资金流向(万元)": -111.62
    },
    {
      "时间": "2026-04-17 14:56",
      "资金流向(万元)": -73.25
    },
    {
      "时间": "2026-04-17 14:57",
      "资金流向(万元)": -73.25
    },
    {
      "时间": "2026-04-17 14:58",
      "资金流向(万元)": -73.25
    },
    {
      "时间": "2026-04-17 14:59",
      "资金流向(万元)": -73.25
    },
    {
      "时间": "2026-04-17 15:00",
      "资金流向(万元)": -838.07
    },
    {
      "时间": "今日汇总",
      "资金流向(万元)": -384205.25
    }
  ],
  "margin": [
    {
      "margin_trading_amt_balance": 3271079887.0,
      "short_selling_amt_balance": 11927577.0,
      "margin_trading_net_buy_amt": -33650660.0,
      "margin_trading_balance": 3259152310.0,
      "margin_trading_buy_amt": 52931668.0,
      "td_date": 1776355200000
    },
    {
      "margin_trading_amt_balance": 3304933852.0,
      "short_selling_amt_balance": 12130880.0,
      "margin_trading_net_buy_amt": -20143738.0,
      "margin_trading_balance": 3292802972.0,
      "margin_trading_buy_amt": 69009063.0,
      "td_date": 1776268800000
    },
    {
      "margin_trading_amt_balance": 3325205589.0,
      "short_selling_amt_balance": 12258880.0,
      "margin_trading_net_buy_amt": 20236882.0,
      "margin_trading_balance": 3312946709.0,
      "margin_trading_buy_amt": 82053146.0,
      "td_date": 1776182400000
    },
    {
      "margin_trading_amt_balance": 3304093137.0,
      "short_selling_amt_balance": 11383311.0,
      "margin_trading_net_buy_amt": 5748184.0,
      "margin_trading_balance": 3292709826.0,
      "margin_trading_buy_amt": 96524400.0,
      "td_date": 1776096000000
    },
    {
      "margin_trading_amt_balance": 3298142083.0,
      "short_selling_amt_balance": 11180441.0,
      "margin_trading_net_buy_amt": 9685387.0,
      "margin_trading_balance": 3286961642.0,
      "margin_trading_buy_amt": 81680995.0,
      "td_date": 1776009600000
    },
    {
      "margin_trading_amt_balance": 3287857472.0,
      "short_selling_amt_balance": 10581215.0,
      "margin_trading_net_buy_amt": -4515529.0,
      "margin_trading_balance": 3277276257.0,
      "margin_trading_buy_amt": 149139442.0,
      "td_date": 1775750400000
    },
    {
      "margin_trading_amt_balance": 3292273275.0,
      "short_selling_amt_balance": 10481492.0,
      "margin_trading_net_buy_amt": 31048747.0,
      "margin_trading_balance": 3281791783.0,
      "margin_trading_buy_amt": 86031630.0,
      "td_date": 1775664000000
    },
    {
      "margin_trading_amt_balance": 3261137805.0,
      "short_selling_amt_balance": 10394769.0,
      "margin_trading_net_buy_amt": 23150712.0,
      "margin_trading_balance": 3250743036.0,
      "margin_trading_buy_amt": 106405297.0,
      "td_date": 1775577600000
    },
    {
      "margin_trading_amt_balance": 3237771827.0,
      "short_selling_amt_balance": 10179504.0,
      "margin_trading_net_buy_amt": -10018671.0,
      "margin_trading_balance": 3227592323.0,
      "margin_trading_buy_amt": 27030952.0,
      "td_date": 1775491200000
    },
    {
      "margin_trading_amt_balance": 3247902674.0,
      "short_selling_amt_balance": 10291680.0,
      "margin_trading_net_buy_amt": -17566436.0,
      "margin_trading_balance": 3237610994.0,
      "margin_trading_buy_amt": 21531600.0,
      "td_date": 1775145600000
    },
    {
      "margin_trading_amt_balance": 3265656182.0,
      "short_selling_amt_balance": 10478752.0,
      "margin_trading_net_buy_amt": -11945116.0,
      "margin_trading_balance": 3255177430.0,
      "margin_trading_buy_amt": 30278116.0,
      "td_date": 1775059200000
    },
    {
      "margin_trading_amt_balance": 3277638327.0,
      "short_selling_amt_balance": 10515780.0,
      "margin_trading_net_buy_amt": -6565201.0,
      "margin_trading_balance": 3267122547.0,
      "margin_trading_buy_amt": 42249521.0,
      "td_date": 1774972800000
    },
    {
      "margin_trading_amt_balance": 3284060587.0,
      "short_selling_amt_balance": 10372839.0,
      "margin_trading_net_buy_amt": -8545854.0,
      "margin_trading_balance": 3273687748.0,
      "margin_trading_buy_amt": 40972663.0,
      "td_date": 1774886400000
    },
    {
      "margin_trading_amt_balance": 3292287914.0,
      "short_selling_amt_balance": 10054311.0,
      "margin_trading_net_buy_amt": 14010338.0,
      "margin_trading_balance": 3282233603.0,
      "margin_trading_buy_amt": 52332132.0,
      "td_date": 1774800000000
    },
    {
      "margin_trading_amt_balance": 3277929896.0,
      "short_selling_amt_balance": 9706631.0,
      "margin_trading_net_buy_amt": -6464357.0,
      "margin_trading_balance": 3268223265.0,
      "margin_trading_buy_amt": 38175323.0,
      "td_date": 1774540800000
    },
    {
      "margin_trading_amt_balance": 3285366571.0,
      "short_selling_amt_balance": 10678950.0,
      "margin_trading_net_buy_amt": -32026179.0,
      "margin_trading_balance": 3274687621.0,
      "margin_trading_buy_amt": 43756390.0,
      "td_date": 1774454400000
    },
    {
      "margin_trading_amt_balance": 3316946081.0,
      "short_selling_amt_balance": 10232280.0,
      "margin_trading_net_buy_amt": -9041528.0,
      "margin_trading_balance": 3306713801.0,
      "margin_trading_buy_amt": 49306733.0,
      "td_date": 1774368000000
    },
    {
      "margin_trading_amt_balance": 3325912071.0,
      "short_selling_amt_balance": 10156742.0,
      "margin_trading_net_buy_amt": -13767698.0,
      "margin_trading_balance": 3315755329.0,
      "margin_trading_buy_amt": 41577893.0,
      "td_date": 1774281600000
    },
    {
      "margin_trading_amt_balance": 3338637589.0,
      "short_selling_amt_balance": 9114560.0,
      "margin_trading_net_buy_amt": -8829605.0,
      "margin_trading_balance": 3329523029.0,
      "margin_trading_buy_amt": 70037226.0,
      "td_date": 1774195200000
    },
    {
      "margin_trading_amt_balance": 3347675552.0,
      "short_selling_amt_balance": 9322920.0,
      "margin_trading_net_buy_amt": -17563177.0,
      "margin_trading_balance": 3338352632.0,
      "margin_trading_buy_amt": 73735896.0,
      "td_date": 1773936000000
    },
    {
      "margin_trading_amt_balance": 3364848733.0,
      "short_selling_amt_balance": 8932924.0,
      "margin_trading_net_buy_amt": -10483473.0,
      "margin_trading_balance": 3355915809.0,
      "margin_trading_buy_amt": 58383451.0,
      "td_date": 1773849600000
    },
    {
      "margin_trading_amt_balance": 3375541427.0,
      "short_selling_amt_balance": 9142144.0,
      "margin_trading_net_buy_amt": -11386757.0,
      "margin_trading_balance": 3366399283.0,
      "margin_trading_buy_amt": 61379371.0,
      "td_date": 1773763200000
    },
    {
      "margin_trading_amt_balance": 3387776538.0,
      "short_selling_amt_balance": 9990500.0,
      "margin_trading_net_buy_amt": 17682192.0,
      "margin_trading_balance": 3377786038.0,
      "margin_trading_buy_amt": 127938446.0,
      "td_date": 1773676800000
    },
    {
      "margin_trading_amt_balance": 3368607333.0,
      "short_selling_amt_balance": 8503488.0,
      "margin_trading_net_buy_amt": -5538787.0,
      "margin_trading_balance": 3360103845.0,
      "margin_trading_buy_amt": 63921741.0,
      "td_date": 1773590400000
    },
    {
      "margin_trading_amt_balance": 3374266274.0,
      "short_selling_amt_balance": 8623640.0,
      "margin_trading_net_buy_amt": -16453041.0,
      "margin_trading_balance": 3365642634.0,
      "margin_trading_buy_amt": 56349258.0,
      "td_date": 1773331200000
    },
    {
      "margin_trading_amt_balance": 3391021434.9,
      "short_selling_amt_balance": 8925757.9,
      "margin_trading_net_buy_amt": -11880409.0,
      "margin_trading_balance": 3382095677.0,
      "margin_trading_buy_amt": 60987435.0,
      "td_date": 1773244800000
    },
    {
      "margin_trading_amt_balance": 3402774618.2,
      "short_selling_amt_balance": 8798533.2,
      "margin_trading_net_buy_amt": -73600071.0,
      "margin_trading_balance": 3393976085.0,
      "margin_trading_buy_amt": 73828756.0,
      "td_date": 1773158400000
    },
    {
      "margin_trading_amt_balance": 3476278975.42,
      "short_selling_amt_balance": 8702820.42,
      "margin_trading_net_buy_amt": 22359157.0,
      "margin_trading_balance": 3467576155.0,
      "margin_trading_buy_amt": 82971494.0,
      "td_date": 1773072000000
    },
    {
      "margin_trading_amt_balance": 3453924959.92,
      "short_selling_amt_balance": 8707961.92,
      "margin_trading_net_buy_amt": -15110411.0,
      "margin_trading_balance": 3445216998.0,
      "margin_trading_buy_amt": 72151897.0,
      "td_date": 1772985600000
    },
    {
      "margin_trading_amt_balance": 3469309305.84,
      "short_selling_amt_balance": 8981896.84,
      "margin_trading_net_buy_amt": -36179192.0,
      "margin_trading_balance": 3460327409.0,
      "margin_trading_buy_amt": 44849892.0,
      "td_date": 1772726400000
    },
    {
      "margin_trading_amt_balance": 3505536363.12,
      "short_selling_amt_balance": 9029763.12,
      "margin_trading_net_buy_amt": 4977209.0,
      "margin_trading_balance": 3496506600.0,
      "margin_trading_buy_amt": 77639229.0,
      "td_date": 1772640000000
    },
    {
      "margin_trading_amt_balance": 3500275602.88,
      "short_selling_amt_balance": 8746211.88,
      "margin_trading_net_buy_amt": 21404045.0,
      "margin_trading_balance": 3491529391.0,
      "margin_trading_buy_amt": 108464866.0,
      "td_date": 1772553600000
    },
    {
      "margin_trading_amt_balance": 3479157164.92,
      "short_selling_amt_balance": 9031817.92,
      "margin_trading_net_buy_amt": -63006417.0,
      "margin_trading_balance": 3470125347.0,
      "margin_trading_buy_amt": 114833935.0,
      "td_date": 1772467200000
    },
    {
      "margin_trading_amt_balance": 3543376996.3,
      "short_selling_amt_balance": 10245231.3,
      "margin_trading_net_buy_amt": 23810510.0,
      "margin_trading_balance": 3533131765.0,
      "margin_trading_buy_amt": 131360740.0,
      "td_date": 1772380800000
    },
    {
      "margin_trading_amt_balance": 3520260361.88,
      "short_selling_amt_balance": 10939107.88,
      "margin_trading_net_buy_amt": -10341993.0,
      "margin_trading_balance": 3509321254.0,
      "margin_trading_buy_amt": 57954629.0,
      "td_date": 1772121600000
    },
    {
      "margin_trading_amt_balance": 3529955347.9,
      "short_selling_amt_balance": 10292100.9,
      "margin_trading_net_buy_amt": -22338494.0,
      "margin_trading_balance": 3519663247.0,
      "margin_trading_buy_amt": 103602995.0,
      "td_date": 1772035200000
    },
    {
      "margin_trading_amt_balance": 3552980561.0,
      "short_selling_amt_balance": 10978821.0,
      "margin_trading_net_buy_amt": -6029364.0,
      "margin_trading_balance": 3542001740.0,
      "margin_trading_buy_amt": 77857343.0,
      "td_date": 1771948800000
    },
    {
      "margin_trading_amt_balance": 3559289803.8,
      "short_selling_amt_balance": 11258700.8,
      "margin_trading_net_buy_amt": 31486327.0,
      "margin_trading_balance": 3548031103.0,
      "margin_trading_buy_amt": 121247649.0,
      "td_date": 1771862400000
    },
    {
      "margin_trading_amt_balance": 3527721033.0,
      "short_selling_amt_balance": 11176256.0,
      "margin_trading_net_buy_amt": -51549922.0,
      "margin_trading_balance": 3516544777.0,
      "margin_trading_buy_amt": 113243909.0,
      "td_date": 1770912000000
    },
    {
      "margin_trading_amt_balance": 3579374434.6,
      "short_selling_amt_balance": 11279735.6,
      "margin_trading_net_buy_amt": -59708038.0,
      "margin_trading_balance": 3568094699.0,
      "margin_trading_buy_amt": 70144492.0,
      "td_date": 1770825600000
    },
    {
      "margin_trading_amt_balance": 3639099039.4,
      "short_selling_amt_balance": 11296302.4,
      "margin_trading_net_buy_amt": -10421870.0,
      "margin_trading_balance": 3627802737.0,
      "margin_trading_buy_amt": 71228315.0,
      "td_date": 1770739200000
    },
    {
      "margin_trading_amt_balance": 3649649597.0,
      "short_selling_amt_balance": 11424989.0,
      "margin_trading_net_buy_amt": 3858249.0,
      "margin_trading_balance": 3638224608.0,
      "margin_trading_buy_amt": 108500669.0,
      "td_date": 1770652800000
    },
    {
      "margin_trading_amt_balance": 3645607462.4,
      "short_selling_amt_balance": 11241104.4,
      "margin_trading_net_buy_amt": -14816727.0,
      "margin_trading_balance": 3634366358.0,
      "margin_trading_buy_amt": 87044005.0,
      "td_date": 1770566400000
    },
    {
      "margin_trading_amt_balance": 3660339093.8,
      "short_selling_amt_balance": 11156009.8,
      "margin_trading_net_buy_amt": -9182417.0,
      "margin_trading_balance": 3649183084.0,
      "margin_trading_buy_amt": 74430155.0,
      "td_date": 1770307200000
    },
    {
      "margin_trading_amt_balance": 3669661744.2,
      "short_selling_amt_balance": 11296243.2,
      "margin_trading_net_buy_amt": -17737798.0,
      "margin_trading_balance": 3658365501.0,
      "margin_trading_buy_amt": 71536675.0,
      "td_date": 1770220800000
    },
    {
      "margin_trading_amt_balance": 3688003513.6,
      "short_selling_amt_balance": 11900213.6,
      "margin_trading_net_buy_amt": -36602650.0,
      "margin_trading_balance": 3676103300.0,
      "margin_trading_buy_amt": 102410581.0,
      "td_date": 1770134400000
    },
    {
      "margin_trading_amt_balance": 3724556466.0,
      "short_selling_amt_balance": 11850516.0,
      "margin_trading_net_buy_amt": 4306784.0,
      "margin_trading_balance": 3712705950.0,
      "margin_trading_buy_amt": 108874032.0,
      "td_date": 1770048000000
    },
    {
      "margin_trading_amt_balance": 3719871005.8,
      "short_selling_amt_balance": 11471840.8,
      "margin_trading_net_buy_amt": -18822262.0,
      "margin_trading_balance": 3708399165.0,
      "margin_trading_buy_amt": 116045686.0,
      "td_date": 1769961600000
    },
    {
      "margin_trading_amt_balance": 3739627144.0,
      "short_selling_amt_balance": 12405717.0,
      "margin_trading_net_buy_amt": 27860208.0,
      "margin_trading_balance": 3727221427.0,
      "margin_trading_buy_amt": 186500885.0,
      "td_date": 1769702400000
    },
    {
      "margin_trading_amt_balance": 3713261198.8,
      "short_selling_amt_balance": 13899979.8,
      "margin_trading_net_buy_amt": -44878075.0,
      "margin_trading_balance": 3699361219.0,
      "margin_trading_buy_amt": 187172979.0,
      "td_date": 1769616000000
    },
    {
      "margin_trading_amt_balance": 3758562009.8,
      "short_selling_amt_balance": 14322716.8,
      "margin_trading_net_buy_amt": 1662145.0,
      "margin_trading_balance": 3744239293.0,
      "margin_trading_buy_amt": 156168963.0,
      "td_date": 1769529600000
    },
    {
      "margin_trading_amt_balance": 3757298316.4,
      "short_selling_amt_balance": 14721168.4,
      "margin_trading_net_buy_amt": -20136800.0,
      "margin_trading_balance": 3742577148.0,
      "margin_trading_buy_amt": 200454873.0,
      "td_date": 1769443200000
    },
    {
      "margin_trading_amt_balance": 3777376658.4,
      "short_selling_amt_balance": 14662710.4,
      "margin_trading_net_buy_amt": -18263426.0,
      "margin_trading_balance": 3762713948.0,
      "margin_trading_buy_amt": 210467134.0,
      "td_date": 1769356800000
    },
    {
      "margin_trading_amt_balance": 3795203182.0,
      "short_selling_amt_balance": 14225808.0,
      "margin_trading_net_buy_amt": -21470656.0,
      "margin_trading_balance": 3780977374.0,
      "margin_trading_buy_amt": 182776810.0,
      "td_date": 1769097600000
    },
    {
      "margin_trading_amt_balance": 3816024328.4,
      "short_selling_amt_balance": 13576298.4,
      "margin_trading_net_buy_amt": 51870965.0,
      "margin_trading_balance": 3802448030.0,
      "margin_trading_buy_amt": 213357974.0,
      "td_date": 1769011200000
    },
    {
      "margin_trading_amt_balance": 3768984060.4,
      "short_selling_amt_balance": 13610264.4,
      "margin_trading_net_buy_amt": -12117230.0,
      "margin_trading_balance": 3755373796.0,
      "margin_trading_buy_amt": 149623237.0,
      "td_date": 1768924800000
    },
    {
      "margin_trading_amt_balance": 3781424322.0,
      "short_selling_amt_balance": 13933296.0,
      "margin_trading_net_buy_amt": 1675417.0,
      "margin_trading_balance": 3767491026.0,
      "margin_trading_buy_amt": 202002180.0,
      "td_date": 1768838400000
    },
    {
      "margin_trading_amt_balance": 3779038306.6,
      "short_selling_amt_balance": 13222697.6,
      "margin_trading_net_buy_amt": -1995729.0,
      "margin_trading_balance": 3765815609.0,
      "margin_trading_buy_amt": 239548552.0,
      "td_date": 1768752000000
    },
    {
      "margin_trading_amt_balance": 3781202226.0,
      "short_selling_amt_balance": 13390888.0,
      "margin_trading_net_buy_amt": 83864046.0,
      "margin_trading_balance": 3767811338.0,
      "margin_trading_buy_amt": 492828441.0,
      "td_date": 1768492800000
    },
    {
      "margin_trading_amt_balance": 3697404982.6,
      "short_selling_amt_balance": 13457689.6,
      "margin_trading_net_buy_amt": -21067887.0,
      "margin_trading_balance": 3683947293.0,
      "margin_trading_buy_amt": 765507274.0,
      "td_date": 1768406400000
    },
    {
      "margin_trading_amt_balance": 3723898959.2,
      "short_selling_amt_balance": 18883780.2,
      "margin_trading_net_buy_amt": 311810822.0,
      "margin_trading_balance": 3705015179.0,
      "margin_trading_buy_amt": 1381064176.0,
      "td_date": 1768320000000
    },
    {
      "margin_trading_amt_balance": 3409834856.6,
      "short_selling_amt_balance": 16630499.6,
      "margin_trading_net_buy_amt": 6374553.0,
      "margin_trading_balance": 3393204357.0,
      "margin_trading_buy_amt": 490735114.0,
      "td_date": 1768233600000
    },
    {
      "margin_trading_amt_balance": 3403564534.8,
      "short_selling_amt_balance": 16734730.8,
      "margin_trading_net_buy_amt": 88411394.0,
      "margin_trading_balance": 3386829804.0,
      "margin_trading_buy_amt": 536640027.0,
      "td_date": 1768147200000
    },
    {
      "margin_trading_amt_balance": 3313424459.4,
      "short_selling_amt_balance": 15006050.4,
      "margin_trading_net_buy_amt": -68169937.0,
      "margin_trading_balance": 3298418409.0,
      "margin_trading_buy_amt": 241438027.0,
      "td_date": 1767888000000
    },
    {
      "margin_trading_amt_balance": 3381050686.2,
      "short_selling_amt_balance": 14462339.2,
      "margin_trading_net_buy_amt": -37438329.0,
      "margin_trading_balance": 3366588347.0,
      "margin_trading_buy_amt": 156130827.0,
      "td_date": 1767801600000
    },
    {
      "margin_trading_amt_balance": 3411049642.4,
      "short_selling_amt_balance": 7022966.4,
      "margin_trading_net_buy_amt": 34148192.0,
      "margin_trading_balance": 3404026676.0,
      "margin_trading_buy_amt": 299100533.0,
      "td_date": 1767715200000
    },
    {
      "margin_trading_amt_balance": 3376816911.6,
      "short_selling_amt_balance": 6938427.6,
      "margin_trading_net_buy_amt": 9378332.0,
      "margin_trading_balance": 3369878484.0,
      "margin_trading_buy_amt": 338666307.0,
      "td_date": 1767628800000
    },
    {
      "margin_trading_amt_balance": 3367598632.8,
      "short_selling_amt_balance": 7098480.8,
      "margin_trading_net_buy_amt": 11022254.0,
      "margin_trading_balance": 3360500152.0,
      "margin_trading_buy_amt": 208742846.0,
      "td_date": 1767542400000
    },
    {
      "margin_trading_amt_balance": 3356449181.0,
      "short_selling_amt_balance": 6971283.0,
      "margin_trading_net_buy_amt": -25411690.0,
      "margin_trading_balance": 3349477898.0,
      "margin_trading_buy_amt": 136174698.0,
      "td_date": 1767110400000
    },
    {
      "margin_trading_amt_balance": 3382672611.4,
      "short_selling_amt_balance": 7783022.4,
      "margin_trading_net_buy_amt": 5335676.0,
      "margin_trading_balance": 3374889589.0,
      "margin_trading_buy_amt": 184957055.0,
      "td_date": 1767024000000
    },
    {
      "margin_trading_amt_balance": 3377497117.0,
      "short_selling_amt_balance": 7943204.0,
      "margin_trading_net_buy_amt": 61174698.0,
      "margin_trading_balance": 3369553913.0,
      "margin_trading_buy_amt": 217757889.0,
      "td_date": 1766937600000
    },
    {
      "margin_trading_amt_balance": 3316200396.4,
      "short_selling_amt_balance": 7821182.4,
      "margin_trading_net_buy_amt": 28436700.0,
      "margin_trading_balance": 3308379214.0,
      "margin_trading_buy_amt": 211079307.0,
      "td_date": 1766678400000
    },
    {
      "margin_trading_amt_balance": 3287990987.2,
      "short_selling_amt_balance": 8048473.2,
      "margin_trading_net_buy_amt": -1064380.0,
      "margin_trading_balance": 3279942514.0,
      "margin_trading_buy_amt": 164587338.0,
      "td_date": 1766592000000
    },
    {
      "margin_trading_amt_balance": 3289912989.8,
      "short_selling_amt_balance": 8906095.8,
      "margin_trading_net_buy_amt": -36786386.0,
      "margin_trading_balance": 3281006894.0,
      "margin_trading_buy_amt": 122077601.0,
      "td_date": 1766505600000
    },
    {
      "margin_trading_amt_balance": 3327168816.0,
      "short_selling_amt_balance": 9375536.0,
      "margin_trading_net_buy_amt": 28098212.0,
      "margin_trading_balance": 3317793280.0,
      "margin_trading_buy_amt": 98972120.0,
      "td_date": 1766419200000
    },
    {
      "margin_trading_amt_balance": 3298125669.2,
      "short_selling_amt_balance": 8430601.2,
      "margin_trading_net_buy_amt": -51204818.0,
      "margin_trading_balance": 3289695068.0,
      "margin_trading_buy_amt": 98321145.0,
      "td_date": 1766332800000
    },
    {
      "margin_trading_amt_balance": 3349816570.6,
      "short_selling_amt_balance": 8916685.6,
      "margin_trading_net_buy_amt": 4007762.0,
      "margin_trading_balance": 3340899885.0,
      "margin_trading_buy_amt": 80993249.0,
      "td_date": 1766073600000
    },
    {
      "margin_trading_amt_balance": 3345606248.6,
      "short_selling_amt_balance": 8714125.6,
      "margin_trading_net_buy_amt": 22936256.0,
      "margin_trading_balance": 3336892123.0,
      "margin_trading_buy_amt": 100704719.0,
      "td_date": 1765987200000
    },
    {
      "margin_trading_amt_balance": 3321727572.4,
      "short_selling_amt_balance": 7771705.4,
      "margin_trading_net_buy_amt": -11847741.0,
      "margin_trading_balance": 3313955867.0,
      "margin_trading_buy_amt": 130639117.0,
      "td_date": 1765900800000
    },
    {
      "margin_trading_amt_balance": 3333656419.2,
      "short_selling_amt_balance": 7852811.2,
      "margin_trading_net_buy_amt": 1427632.0,
      "margin_trading_balance": 3325803608.0,
      "margin_trading_buy_amt": 89512409.0,
      "td_date": 1765814400000
    },
    {
      "margin_trading_amt_balance": 3332199691.2,
      "short_selling_amt_balance": 7823715.2,
      "margin_trading_net_buy_amt": 10192688.0,
      "margin_trading_balance": 3324375976.0,
      "margin_trading_buy_amt": 70957753.0,
      "td_date": 1765728000000
    },
    {
      "margin_trading_amt_balance": 3322638436.0,
      "short_selling_amt_balance": 8455148.0,
      "margin_trading_net_buy_amt": -14739431.0,
      "margin_trading_balance": 3314183288.0,
      "margin_trading_buy_amt": 75493640.0,
      "td_date": 1765468800000
    },
    {
      "margin_trading_amt_balance": 3337484099.0,
      "short_selling_amt_balance": 8561380.0,
      "margin_trading_net_buy_amt": 4625233.0,
      "margin_trading_balance": 3328922719.0,
      "margin_trading_buy_amt": 84735224.0,
      "td_date": 1765382400000
    },
    {
      "margin_trading_amt_balance": 3332958601.0,
      "short_selling_amt_balance": 8661114.0,
      "margin_trading_net_buy_amt": 19049009.0,
      "margin_trading_balance": 3324297487.0,
      "margin_trading_buy_amt": 113344486.0,
      "td_date": 1765296000000
    },
    {
      "margin_trading_amt_balance": 3313804402.4,
      "short_selling_amt_balance": 8555924.4,
      "margin_trading_net_buy_amt": 17186866.0,
      "margin_trading_balance": 3305248478.0,
      "margin_trading_buy_amt": 95848498.0,
      "td_date": 1765209600000
    },
    {
      "margin_trading_amt_balance": 3296451589.6,
      "short_selling_amt_balance": 8389977.6,
      "margin_trading_net_buy_amt": 8978114.0,
      "margin_trading_balance": 3288061612.0,
      "margin_trading_buy_amt": 169653563.0,
      "td_date": 1765123200000
    },
    {
      "margin_trading_amt_balance": 3287647295.6,
      "short_selling_amt_balance": 8563797.6,
      "margin_trading_net_buy_amt": 2839013.0,
      "margin_trading_balance": 3279083498.0,
      "margin_trading_buy_amt": 158594774.0,
      "td_date": 1764864000000
    },
    {
      "margin_trading_amt_balance": 3284834543.4,
      "short_selling_amt_balance": 8590058.4,
      "margin_trading_net_buy_amt": -18078822.0,
      "margin_trading_balance": 3276244485.0,
      "margin_trading_buy_amt": 37627730.0,
      "td_date": 1764777600000
    },
    {
      "margin_trading_amt_balance": 3307192993.8,
      "short_selling_amt_balance": 12869686.8,
      "margin_trading_net_buy_amt": -21794416.0,
      "margin_trading_balance": 3294323307.0,
      "margin_trading_buy_amt": 70809721.0,
      "td_date": 1764691200000
    },
    {
      "margin_trading_amt_balance": 3327889978.6,
      "short_selling_amt_balance": 11772255.6,
      "margin_trading_net_buy_amt": 24878829.0,
      "margin_trading_balance": 3316117723.0,
      "margin_trading_buy_amt": 86824100.0,
      "td_date": 1764604800000
    },
    {
      "margin_trading_amt_balance": 3303789754.8,
      "short_selling_amt_balance": 12550860.8,
      "margin_trading_net_buy_amt": 1036900.0,
      "margin_trading_balance": 3291238894.0,
      "margin_trading_buy_amt": 88934346.0,
      "td_date": 1764518400000
    },
    {
      "margin_trading_amt_balance": 3304061675.28,
      "short_selling_amt_balance": 13859681.28,
      "margin_trading_net_buy_amt": -24236754.0,
      "margin_trading_balance": 3290201994.0,
      "margin_trading_buy_amt": 62271404.0,
      "td_date": 1764259200000
    },
    {
      "margin_trading_amt_balance": 3328190436.96,
      "short_selling_amt_balance": 13751688.96,
      "margin_trading_net_buy_amt": -13086691.0,
      "margin_trading_balance": 3314438748.0,
      "margin_trading_buy_amt": 88975661.0,
      "td_date": 1764172800000
    },
    {
      "margin_trading_amt_balance": 3341525165.44,
      "short_selling_amt_balance": 13999726.44,
      "margin_trading_net_buy_amt": -2474541.0,
      "margin_trading_balance": 3327525439.0,
      "margin_trading_buy_amt": 102573793.0,
      "td_date": 1764086400000
    },
    {
      "margin_trading_amt_balance": 3344054138.8,
      "short_selling_amt_balance": 14054158.8,
      "margin_trading_net_buy_amt": -3480458.0,
      "margin_trading_balance": 3329999980.0,
      "margin_trading_buy_amt": 146285541.0,
      "td_date": 1764000000000
    },
    {
      "margin_trading_amt_balance": 3343383706.0,
      "short_selling_amt_balance": 9903268.0,
      "margin_trading_net_buy_amt": -39782723.0,
      "margin_trading_balance": 3333480438.0,
      "margin_trading_buy_amt": 111089957.0,
      "td_date": 1763913600000
    },
    {
      "margin_trading_amt_balance": 3383250979.4,
      "short_selling_amt_balance": 9987818.4,
      "margin_trading_net_buy_amt": 6151212.0,
      "margin_trading_balance": 3373263161.0,
      "margin_trading_buy_amt": 119011324.0,
      "td_date": 1763654400000
    },
    {
      "margin_trading_amt_balance": 3376666770.92,
      "short_selling_amt_balance": 9554821.92,
      "margin_trading_net_buy_amt": -25476905.0,
      "margin_trading_balance": 3367111949.0,
      "margin_trading_buy_amt": 90278991.0,
      "td_date": 1763568000000
    },
    {
      "margin_trading_amt_balance": 3402008564.04,
      "short_selling_amt_balance": 9419710.04,
      "margin_trading_net_buy_amt": 34637006.0,
      "margin_trading_balance": 3392588854.0,
      "margin_trading_buy_amt": 125145713.0,
      "td_date": 1763481600000
    },
    {
      "margin_trading_amt_balance": 3366868127.2,
      "short_selling_amt_balance": 8916279.2,
      "margin_trading_net_buy_amt": 53518190.0,
      "margin_trading_balance": 3357951848.0,
      "margin_trading_buy_amt": 202538412.0,
      "td_date": 1763395200000
    },
    {
      "margin_trading_amt_balance": 3312325027.92,
      "short_selling_amt_balance": 7891369.92,
      "margin_trading_net_buy_amt": -2879278.0,
      "margin_trading_balance": 3304433658.0,
      "margin_trading_buy_amt": 55315502.0,
      "td_date": 1763308800000
    },
    {
      "margin_trading_amt_balance": 3315266867.44,
      "short_selling_amt_balance": 7953931.44,
      "margin_trading_net_buy_amt": 7764248.0,
      "margin_trading_balance": 3307312936.0,
      "margin_trading_buy_amt": 67261675.0,
      "td_date": 1763049600000
    },
    {
      "margin_trading_amt_balance": 3304421601.2,
      "short_selling_amt_balance": 4872913.2,
      "margin_trading_net_buy_amt": -10547956.0,
      "margin_trading_balance": 3299548688.0,
      "margin_trading_buy_amt": 85314611.0,
      "td_date": 1762963200000
    },
    {
      "margin_trading_amt_balance": 3315052999.8,
      "short_selling_amt_balance": 4956355.8,
      "margin_trading_net_buy_amt": -9679490.0,
      "margin_trading_balance": 3310096644.0,
      "margin_trading_buy_amt": 58640162.0,
      "td_date": 1762876800000
    },
    {
      "margin_trading_amt_balance": 3324906043.52,
      "short_selling_amt_balance": 5129909.52,
      "margin_trading_net_buy_amt": -76235813.0,
      "margin_trading_balance": 3319776134.0,
      "margin_trading_buy_amt": 112232190.0,
      "td_date": 1762790400000
    },
    {
      "margin_trading_amt_balance": 3400638578.24,
      "short_selling_amt_balance": 4626631.24,
      "margin_trading_net_buy_amt": -21528993.0,
      "margin_trading_balance": 3396011947.0,
      "margin_trading_buy_amt": 79465121.0,
      "td_date": 1762704000000
    },
    {
      "margin_trading_amt_balance": 3422555723.48,
      "short_selling_amt_balance": 5014784.48,
      "margin_trading_net_buy_amt": -11476828.0,
      "margin_trading_balance": 3417540939.0,
      "margin_trading_buy_amt": 78710609.0,
      "td_date": 1762444800000
    },
    {
      "margin_trading_amt_balance": 3434056287.32,
      "short_selling_amt_balance": 5038520.32,
      "margin_trading_net_buy_amt": -18502958.0,
      "margin_trading_balance": 3429017767.0,
      "margin_trading_buy_amt": 78531296.0,
      "td_date": 1762358400000
    },
    {
      "margin_trading_amt_balance": 3453009990.6,
      "short_selling_amt_balance": 5489265.6,
      "margin_trading_net_buy_amt": 23121964.0,
      "margin_trading_balance": 3447520725.0,
      "margin_trading_buy_amt": 133601917.0,
      "td_date": 1762272000000
    },
    {
      "margin_trading_amt_balance": 3431494125.8,
      "short_selling_amt_balance": 7095364.8,
      "margin_trading_net_buy_amt": 8674525.0,
      "margin_trading_balance": 3424398761.0,
      "margin_trading_buy_amt": 135487967.0,
      "td_date": 1762185600000
    },
    {
      "margin_trading_amt_balance": 3423311807.2,
      "short_selling_amt_balance": 7587571.2,
      "margin_trading_net_buy_amt": -22165052.0,
      "margin_trading_balance": 3415724236.0,
      "margin_trading_buy_amt": 98238678.0,
      "td_date": 1762099200000
    },
    {
      "margin_trading_amt_balance": 3443847183.8,
      "short_selling_amt_balance": 5957894.8,
      "margin_trading_net_buy_amt": -7035106.0,
      "margin_trading_balance": 3437889289.0,
      "margin_trading_buy_amt": 141391718.0,
      "td_date": 1761840000000
    },
    {
      "margin_trading_amt_balance": 3451458423.6,
      "short_selling_amt_balance": 6534028.6,
      "margin_trading_net_buy_amt": -10204410.0,
      "margin_trading_balance": 3444924395.0,
      "margin_trading_buy_amt": 153725164.0,
      "td_date": 1761753600000
    },
    {
      "margin_trading_amt_balance": 3462607185.8,
      "short_selling_amt_balance": 7478380.8,
      "margin_trading_net_buy_amt": -41456573.0,
      "margin_trading_balance": 3455128805.0,
      "margin_trading_buy_amt": 152734223.0,
      "td_date": 1761667200000
    },
    {
      "margin_trading_amt_balance": 3504929755.6,
      "short_selling_amt_balance": 8344377.6,
      "margin_trading_net_buy_amt": 12231223.0,
      "margin_trading_balance": 3496585378.0,
      "margin_trading_buy_amt": 125778698.0,
      "td_date": 1761580800000
    },
    {
      "margin_trading_amt_balance": 3492488255.0,
      "short_selling_amt_balance": 8134100.0,
      "margin_trading_net_buy_amt": 13699344.0,
      "margin_trading_balance": 3484354155.0,
      "margin_trading_buy_amt": 142515226.0,
      "td_date": 1761494400000
    },
    {
      "margin_trading_amt_balance": 3479516941.2,
      "short_selling_amt_balance": 8862131.2,
      "margin_trading_net_buy_amt": -7450871.0,
      "margin_trading_balance": 3470654810.0,
      "margin_trading_buy_amt": 115662896.0,
      "td_date": 1761235200000
    },
    {
      "margin_trading_amt_balance": 3486964353.8,
      "short_selling_amt_balance": 8858672.8,
      "margin_trading_net_buy_amt": 315565.0,
      "margin_trading_balance": 3478105681.0,
      "margin_trading_buy_amt": 94811308.0,
      "td_date": 1761148800000
    },
    {
      "margin_trading_amt_balance": 3486938728.8,
      "short_selling_amt_balance": 9148612.8,
      "margin_trading_net_buy_amt": 3554284.0,
      "margin_trading_balance": 3477790116.0,
      "margin_trading_buy_amt": 65947998.0,
      "td_date": 1761062400000
    },
    {
      "margin_trading_amt_balance": 3483249451.4,
      "short_selling_amt_balance": 9013619.4,
      "margin_trading_net_buy_amt": 28916720.0,
      "margin_trading_balance": 3474235832.0,
      "margin_trading_buy_amt": 123185025.0,
      "td_date": 1760976000000
    }
  ],
  "block_trans": [
    {
      "vol": 2535700.0,
      "sell_branch_org_name": "国泰海通证券股份有限公司杭州富春路证券营业部",
      "premium_rat": 0.63,
      "trans_amt": 64305500.0,
      "td_date": 1775145600000,
      "buy_branch_org_name": "国泰海通证券股份有限公司杭州富春路证券营业部",
      "trans_price": 25.36
    },
    {
      "vol": 297400.0,
      "sell_branch_org_name": "国泰海通证券股份有限公司杭州富春路证券营业部",
      "premium_rat": -7.79,
      "trans_amt": 8164500.0,
      "td_date": 1770307200000,
      "buy_branch_org_name": "国泰海通证券股份有限公司杭州富春路证券营业部",
      "trans_price": 27.45
    },
    {
      "vol": 328300.0,
      "sell_branch_org_name": "海通证券股份有限公司杭州富春路证券营业部",
      "premium_rat": 0.0,
      "trans_amt": 11557100.0,
      "td_date": 1757260800000,
      "buy_branch_org_name": "海通证券股份有限公司杭州富春路证券营业部",
      "trans_price": 35.2
    },
    {
      "vol": 158100.0,
      "sell_branch_org_name": "中国国际金融股份有限公司北京建国门外大街证券营业部",
      "premium_rat": 0.0,
      "trans_amt": 5370500.0,
      "td_date": 1756915200000,
      "buy_branch_org_name": "海通证券股份有限公司杭州富春路证券营业部",
      "trans_price": 33.98
    },
    {
      "vol": 158100.0,
      "sell_branch_org_name": "中国国际金融股份有限公司北京建国门外大街证券营业部",
      "premium_rat": 0.0,
      "trans_amt": 5370500.0,
      "td_date": 1756915200000,
      "buy_branch_org_name": "海通证券股份有限公司杭州富春路证券营业部",
      "trans_price": 33.98
    },
    {
      "vol": 600000.0,
      "sell_branch_org_name": "海通证券股份有限公司杭州富春路证券营业部",
      "premium_rat": 0.0,
      "trans_amt": 23196000.0,
      "td_date": 1756656000000,
      "buy_branch_org_name": "海通证券股份有限公司杭州富春路证券营业部",
      "trans_price": 38.66
    },
    {
      "vol": 615000.0,
      "sell_branch_org_name": "海通证券股份有限公司杭州富春路证券营业部",
      "premium_rat": 0.0,
      "trans_amt": 23652900.0,
      "td_date": 1755792000000,
      "buy_branch_org_name": "海通证券股份有限公司杭州富春路证券营业部",
      "trans_price": 38.46
    },
    {
      "vol": 113000.0,
      "sell_branch_org_name": "海通证券股份有限公司杭州富春路证券营业部",
      "premium_rat": 0.0,
      "trans_amt": 4254500.0,
      "td_date": 1755446400000,
      "buy_branch_org_name": "海通证券股份有限公司杭州富春路证券营业部",
      "trans_price": 37.65
    },
    {
      "vol": 500000.0,
      "sell_branch_org_name": "中国国际金融股份有限公司北京建国门外大街证券营业部",
      "premium_rat": 0.0,
      "trans_amt": 18430000.0,
      "td_date": 1755187200000,
      "buy_branch_org_name": "海通证券股份有限公司杭州富春路证券营业部",
      "trans_price": 36.86
    },
    {
      "vol": 740000.0,
      "sell_branch_org_name": "中国国际金融股份有限公司北京建国门外大街证券营业部",
      "premium_rat": 0.0,
      "trans_amt": 25463400.0,
      "td_date": 1754582400000,
      "buy_branch_org_name": "海通证券股份有限公司杭州富春路证券营业部",
      "trans_price": 34.41
    },
    {
      "vol": 120000.0,
      "sell_branch_org_name": "中国中金财富证券有限公司福州五四路证券营业部",
      "premium_rat": 0.0,
      "trans_amt": 3972000.0,
      "td_date": 1753027200000,
      "buy_branch_org_name": "中国国际金融股份有限公司北京建国门外大街证券营业部",
      "trans_price": 33.1
    },
    {
      "vol": 619000.0,
      "sell_branch_org_name": "海通证券股份有限公司杭州富春路证券营业部",
      "premium_rat": -7.18,
      "trans_amt": 16094000.0,
      "td_date": 1750348800000,
      "buy_branch_org_name": "海通证券股份有限公司杭州富春路证券营业部",
      "trans_price": 26.0
    },
    {
      "vol": 556400.0,
      "sell_branch_org_name": "国泰海通证券股份有限公司总部",
      "premium_rat": 0.0,
      "trans_amt": 16024300.0,
      "td_date": 1750262400000,
      "buy_branch_org_name": "海通证券股份有限公司杭州富春路证券营业部",
      "trans_price": 28.8
    },
    {
      "vol": 120000.0,
      "sell_branch_org_name": "中国国际金融股份有限公司深圳分公司",
      "premium_rat": 0.0,
      "trans_amt": 3456000.0,
      "td_date": 1750262400000,
      "buy_branch_org_name": "中国国际金融股份有限公司北京建国门外大街证券营业部",
      "trans_price": 28.8
    },
    {
      "vol": 569000.0,
      "sell_branch_org_name": "海通证券股份有限公司杭州富春路证券营业部",
      "premium_rat": -7.8,
      "trans_amt": 15676000.0,
      "td_date": 1750176000000,
      "buy_branch_org_name": "海通证券股份有限公司杭州富春路证券营业部",
      "trans_price": 27.55
    },
    {
      "vol": 120000.0,
      "sell_branch_org_name": "中国国际金融股份有限公司北京建国门外大街证券营业部",
      "premium_rat": 0.0,
      "trans_amt": 3663600.0,
      "td_date": 1750003200000,
      "buy_branch_org_name": "国泰海通证券股份有限公司深圳福华三路证券营业部",
      "trans_price": 30.53
    },
    {
      "vol": 555000.0,
      "sell_branch_org_name": "海通证券股份有限公司杭州富春路证券营业部",
      "premium_rat": -3.86,
      "trans_amt": 14097000.0,
      "td_date": 1749571200000,
      "buy_branch_org_name": "海通证券股份有限公司杭州富春路证券营业部",
      "trans_price": 25.4
    },
    {
      "vol": 1160000.0,
      "sell_branch_org_name": "国泰海通证券股份有限公司总部",
      "premium_rat": 0.0,
      "trans_amt": 31436000.0,
      "td_date": 1749398400000,
      "buy_branch_org_name": "海通证券股份有限公司杭州富春路证券营业部",
      "trans_price": 27.1
    },
    {
      "vol": 82899.99999999999,
      "sell_branch_org_name": "海通证券股份有限公司上海嘉定区洪德路证券营业部",
      "premium_rat": 0.0,
      "trans_amt": 2114000.0,
      "td_date": 1747929600000,
      "buy_branch_org_name": "国泰海通证券股份有限公司总部",
      "trans_price": 25.5
    },
    {
      "vol": 950500.0,
      "sell_branch_org_name": "国泰海通证券股份有限公司总部",
      "premium_rat": 0.0,
      "trans_amt": 24931600.0,
      "td_date": 1747670400000,
      "buy_branch_org_name": "海通证券股份有限公司杭州富春路证券营业部",
      "trans_price": 26.23
    },
    {
      "vol": 866900.0,
      "sell_branch_org_name": "海通证券股份有限公司公司总部",
      "premium_rat": 0.0,
      "trans_amt": 26639800.0,
      "td_date": 1742313600000,
      "buy_branch_org_name": "国泰君安证券股份有限公司总部",
      "trans_price": 30.73
    },
    {
      "vol": 900000.0,
      "sell_branch_org_name": "海通证券股份有限公司公司总部",
      "premium_rat": 0.0,
      "trans_amt": 27945000.0,
      "td_date": 1742227200000,
      "buy_branch_org_name": "国泰君安证券股份有限公司总部",
      "trans_price": 31.05
    },
    {
      "vol": 900000.0,
      "sell_branch_org_name": "海通证券股份有限公司公司总部",
      "premium_rat": 0.0,
      "trans_amt": 27999000.0,
      "td_date": 1742140800000,
      "buy_branch_org_name": "国泰君安证券股份有限公司总部",
      "trans_price": 31.11
    },
    {
      "vol": 82899.99999999999,
      "sell_branch_org_name": "国泰君安证券股份有限公司总部",
      "premium_rat": 0.0,
      "trans_amt": 2726600.0000000005,
      "td_date": 1739289600000,
      "buy_branch_org_name": "海通证券股份有限公司上海嘉定区洪德路证券营业部",
      "trans_price": 32.89
    },
    {
      "vol": 470000.0,
      "sell_branch_org_name": "招商证券股份有限公司北京景辉街证券营业部",
      "premium_rat": 0.0,
      "trans_amt": 12417400.0,
      "td_date": 1735747200000,
      "buy_branch_org_name": "招商证券股份有限公司北京景辉街证券营业部",
      "trans_price": 26.42
    },
    {
      "vol": 170100.00000000003,
      "sell_branch_org_name": "中国国际金融股份有限公司北京建国门外大街证券营业部",
      "premium_rat": 0.0,
      "trans_amt": 5218700.0,
      "td_date": 1732809600000,
      "buy_branch_org_name": "中国中金财富证券有限公司福州五四路证券营业部",
      "trans_price": 30.68
    },
    {
      "vol": 70000.0,
      "sell_branch_org_name": "中信证券股份有限公司上海分公司",
      "premium_rat": 0.0,
      "trans_amt": 2100000.0,
      "td_date": 1731945600000,
      "buy_branch_org_name": "华泰证券股份有限公司总部",
      "trans_price": 30.0
    },
    {
      "vol": 635600.0,
      "sell_branch_org_name": "海通证券股份有限公司杭州富春路证券营业部",
      "premium_rat": 0.06,
      "trans_amt": 10169100.0,
      "td_date": 1724083200000,
      "buy_branch_org_name": "海通证券股份有限公司杭州富春路证券营业部",
      "trans_price": 16.0
    },
    {
      "vol": 724000.0,
      "sell_branch_org_name": "海通证券股份有限公司杭州富春路证券营业部",
      "premium_rat": -0.06,
      "trans_amt": 12199400.0,
      "td_date": 1723478400000,
      "buy_branch_org_name": "海通证券股份有限公司杭州富春路证券营业部",
      "trans_price": 16.85
    },
    {
      "vol": 698000.0,
      "sell_branch_org_name": "海通证券股份有限公司杭州富春路证券营业部",
      "premium_rat": -0.35,
      "trans_amt": 12005600.0,
      "td_date": 1723046400000,
      "buy_branch_org_name": "海通证券股份有限公司杭州富春路证券营业部",
      "trans_price": 17.2
    }
  ],
  "holders": [
    {
      "per_float_chg": -6.25,
      "per_float": 7894.613390739683,
      "top_float_holder_ratio": NaN,
      "chg": 6.67,
      "price": 30.02,
      "ashare_holder": 239927,
      "per_amount": 236996.2939900053,
      "top_holder_ratio": NaN,
      "timestamp": 1772208000000
    },
    {
      "per_float_chg": -4.96,
      "per_float": 8421.316404426443,
      "top_float_holder_ratio": 35.6513,
      "chg": 5.22,
      "price": 30.15,
      "ashare_holder": 224921,
      "per_amount": 253902.68959345724,
      "top_holder_ratio": 35.65,
      "timestamp": 1767110400000
    },
    {
      "per_float_chg": -0.03,
      "per_float": 8860.72643111425,
      "top_float_holder_ratio": NaN,
      "chg": 0.0,
      "price": 29.32,
      "ashare_holder": 213767,
      "per_amount": 259796.49896026982,
      "top_holder_ratio": NaN,
      "timestamp": 1764259200000
    },
    {
      "per_float_chg": -5.59,
      "per_float": 8863.54866279641,
      "top_float_holder_ratio": 36.4741,
      "chg": 6.09,
      "price": 34.52,
      "ashare_holder": 213767,
      "per_amount": 305969.6998397321,
      "top_holder_ratio": 36.480000000000004,
      "timestamp": 1759161600000
    },
    {
      "per_float_chg": NaN,
      "per_float": 9388.517389750767,
      "top_float_holder_ratio": 38.0386,
      "chg": NaN,
      "price": 33.54,
      "ashare_holder": 201498,
      "per_amount": 314890.8732522407,
      "top_holder_ratio": 38.03,
      "timestamp": 1751212800000
    }
  ]
}